MANIFEST.in
Makefile
README.md
entry.cpp
entry.hpp
httpheader.cpp
httpheader.hpp
main.cpp
pymain.cpp
setup.py
simple.cpp
simple.hpp
structs.hpp
util.cpp
util.hpp
chromesimplecache.egg-info/PKG-INFO
chromesimplecache.egg-info/SOURCES.txt
chromesimplecache.egg-info/dependency_links.txt
chromesimplecache.egg-info/requires.txt
chromesimplecache.egg-info/top_level.txt
simplecache/__init__.py
simplecache/helper.py